cimsparql/__init__.py
cimsparql/adaptions.py
cimsparql/constants.py
cimsparql/data_models.py
cimsparql/graphdb.py
cimsparql/local_client.py
cimsparql/model.py
cimsparql/retry_cb.py
cimsparql/sparql_result_json.py
cimsparql/templates.py
cimsparql/type_mapper.py
cimsparql/url.py
cimsparql/utils.py
cimsparql/value_mapper.py
cimsparql/sparql/ac_lines.sparql
cimsparql/sparql/add_mrid.sparql
cimsparql/sparql/associated_switches.sparql
cimsparql/sparql/base_voltage.sparql
cimsparql/sparql/borders.sparql
cimsparql/sparql/branch_node_withdraw.sparql
cimsparql/sparql/bus.sparql
cimsparql/sparql/busbar_section.sparql
cimsparql/sparql/connections.sparql
cimsparql/sparql/connectivity_nodes.sparql
cimsparql/sparql/converter_hvdc_bidzones.sparql
cimsparql/sparql/converters.sparql
cimsparql/sparql/coordinates.sparql
cimsparql/sparql/dc_active_power_flow.sparql
cimsparql/sparql/disconnected.sparql
cimsparql/sparql/exchange.sparql
cimsparql/sparql/full_model.sparql
cimsparql/sparql/gen_unit_and_sync_machine_mapping.sparql
cimsparql/sparql/hvdc.sparql
cimsparql/sparql/loads.sparql
cimsparql/sparql/market_dates.sparql
cimsparql/sparql/phase_tap_changer.sparql
cimsparql/sparql/power_flow.sparql
cimsparql/sparql/ras_equipment.sparql
cimsparql/sparql/regions.sparql
cimsparql/sparql/series_compensators.sparql
cimsparql/sparql/station_group_code_and_names.sparql
cimsparql/sparql/station_group_for_power_unit.sparql
cimsparql/sparql/substation_voltage_level.sparql
cimsparql/sparql/sv_branch.sparql
cimsparql/sparql/sv_injection.sparql
cimsparql/sparql/sv_power_deviation.sparql
cimsparql/sparql/switches.sparql
cimsparql/sparql/synchronous_machines.sparql
cimsparql/sparql/transformer_branches.sparql
cimsparql/sparql/transformer_center_nodes.sparql
cimsparql/sparql/transformer_winding_angle.sparql
cimsparql/sparql/transformer_windings.sparql
cimsparql/sparql/transformers.sparql
cimsparql/sparql/transformers_connected_to_converter.sparql
cimsparql/sparql/type_mapper.sparql
cimsparql-9.11.2.dist-info/licenses/LICENSE
cimsparql-9.11.2.dist-info/METADATA
cimsparql-9.11.2.dist-info/WHEEL
cimsparql-9.11.2.dist-info/top_level.txt
cimsparql-9.11.2.dist-info/RECORD
