Metadata-Version: 2.4
Name: cimsparql
Version: 9.11.2
Summary: CIM query utilities
Author-email: Statnett Datascience <Datascience.Drift@Statnett.no>
Requires-Python: >=3.11
License-File: LICENSE
Requires-Dist: httpx>=0.27.2
Requires-Dist: numpy>=1.9.0
Requires-Dist: pandas>=2.2.3
Requires-Dist: pandera[pandas]>=0.24.0
Requires-Dist: polyfactory>=2.17.0
Requires-Dist: pydantic>=2.9.2
Requires-Dist: pyoxigraph>=0.5.2
Requires-Dist: sparqlwrapper>=2.0.0
Requires-Dist: tenacity>=9.0.0
Dynamic: license-file
